lebai_robot_voice_sdk/__init__.py
lebai_robot_voice_sdk/base_voice.py
lebai_robot_voice_sdk/errors.py
lebai_robot_voice_sdk/main.py
lebai_robot_voice_sdk/assets/mp3/机械臂急停.mp3
lebai_robot_voice_sdk/assets/mp3/欢迎语音.mp3
lebai_robot_voice_sdk/assets/mp3/汤面请等待加汤.mp3
lebai_robot_voice_sdk/assets/mp3/请清理料盒筐.mp3
lebai_robot_voice_sdk/assets/mp3/bowl_was_tokenaway/1号位碗被拿走.mp3
lebai_robot_voice_sdk/assets/mp3/bowl_was_tokenaway/2号位碗被拿走.mp3
lebai_robot_voice_sdk/assets/mp3/bowl_was_tokenaway/3号位碗被拿走.mp3
lebai_robot_voice_sdk/assets/mp3/bowl_was_tokenaway/4号位碗被拿走.mp3
lebai_robot_voice_sdk/assets/mp3/bowl_was_tokenaway/5号位碗被拿走.mp3
lebai_robot_voice_sdk/assets/mp3/cabinet_lack/面柜1层缺料.mp3
lebai_robot_voice_sdk/assets/mp3/cabinet_lack/面柜2层缺料.mp3
lebai_robot_voice_sdk/assets/mp3/cabinet_lack/面柜3层缺料.mp3
lebai_robot_voice_sdk/assets/mp3/cabinet_lack/面柜4层缺料.mp3
lebai_robot_voice_sdk/assets/mp3/cabinet_lack/面柜已空.mp3
lebai_robot_voice_sdk/assets/mp3/order/1号下单.mp3
lebai_robot_voice_sdk/assets/mp3/order/2号下单.mp3
lebai_robot_voice_sdk/assets/mp3/order/3号下单.mp3
lebai_robot_voice_sdk/assets/mp3/order/4号下单.mp3
lebai_robot_voice_sdk/assets/mp3/order/5号下单.mp3
lebai_robot_voice_sdk/assets/mp3/take_food/1号取餐.mp3
lebai_robot_voice_sdk/assets/mp3/take_food/2号取餐.mp3
lebai_robot_voice_sdk/assets/mp3/take_food/3号取餐.mp3
lebai_robot_voice_sdk/assets/mp3/take_food/4号取餐.mp3
lebai_robot_voice_sdk/assets/mp3/take_food/5号取餐.mp3
lebai_robot_voice_sdk-0.1.1.dist-info/METADATA
lebai_robot_voice_sdk-0.1.1.dist-info/WHEEL
lebai_robot_voice_sdk-0.1.1.dist-info/top_level.txt
lebai_robot_voice_sdk-0.1.1.dist-info/RECORD
