Metadata-Version: 2.1
Name: lebai_robot_voice_sdk
Version: 0.1.1
Summary: 乐白机器人语音播报SDK
Author-email: 张庆风 <aurora.xiaofeng@zohomail.cn>
License: MIT
Keywords: lebai,robot,voice,audio,turntable
Classifier: Development Status :: 4 - Beta
Classifier: Intended Audience :: Developers
Classifier: License :: OSI Approved :: MIT License
Classifier: Programming Language :: Python :: 3
Classifier: Programming Language :: Python :: 3.7
Classifier: Programming Language :: Python :: 3.8
Classifier: Programming Language :: Python :: 3.9
Classifier: Programming Language :: Python :: 3.10
Classifier: Programming Language :: Python :: 3.11
Requires-Python: >=3.7
Requires-Dist: miniaudio>=1.61
Provides-Extra: dev
Requires-Dist: pytest>=7.0; extra == "dev"
Requires-Dist: black; extra == "dev"
Requires-Dist: flake8; extra == "dev"
